LICENSE
README.md
setup.cfg
setup.py
aioaquacell/__init__.py
aioaquacell/aquacell_api.py
aioaquacell/authentication_tokens.py
aioaquacell/aws_cognito_authenticator.py
aioaquacell/aws_credentials.py
aioaquacell/aws_signature_request.py
aioaquacell/brand_credentials.py
aioaquacell/const.py
aioaquacell/exceptions.py
aioaquacell/py.typed
aioaquacell/softener.py
aioaquacell.egg-info/PKG-INFO
aioaquacell.egg-info/SOURCES.txt
aioaquacell.egg-info/dependency_links.txt
aioaquacell.egg-info/requires.txt
aioaquacell.egg-info/top_level.txt