Metadata-Version: 2.1
Name: aioaquacell
Version: 0.1.9
Summary: Asynchronous library to retrieve details of your Aquacell water softener device
Home-page: https://github.com/Jordi1990/aioaquacell
Download-URL: https://github.com/Jordi1990/aioaquacell/archive/refs/tags/v0.1.9.tar.gz
Author: Jordi Epema
Author-email: jordi.epema@gmail.com
License: Apache License 2.0
License-File: LICENSE
Requires-Dist: aiohttp
Requires-Dist: requests_aws4auth
Requires-Dist: pycognito
Requires-Dist: aws_request_signer
Requires-Dist: aiobotocore
Requires-Dist: botocore
Requires-Dist: boto3
Requires-Dist: attr
